adhocboost/AdHocBoost.py
adhocboost/__init__.py
adhocboost/test.py
adhocboost-0.0.6.dist-info/LICENSE
adhocboost-0.0.6.dist-info/METADATA
adhocboost-0.0.6.dist-info/WHEEL
adhocboost-0.0.6.dist-info/top_level.txt
adhocboost-0.0.6.dist-info/RECORD
