Metadata-Version: 2.1
Name: adhocboost
Version: 0.0.6
Summary: A model specialized for imbalanced class learning.
Home-page: https://github.com/deliveryhero/adhocboost/
Author: Benjamin Feifke
Author-email: benjamin.feifke@deliveryhero.com
License: UNKNOWN
Project-URL: Bug Tracker, https://github.com/deliveryhero/adhocboost/issues
Platform: UNKNOWN
Classifier: Programming Language :: Python :: 3
Classifier: License :: OSI Approved :: MIT License
Classifier: Operating System :: OS Independent
Requires-Python: >=3.6
License-File: LICENSE
